base-decryptor/__init__.py
base-decryptor/__main__.py
base-decryptor/decode.py
base-decryptor/main.py
base-decryptor/decoders/__init__.py
base-decryptor/decoders/base122_decoder.py
base-decryptor/decoders/base32_decoder.py
base-decryptor/decoders/base36_decoder.py
base-decryptor/decoders/base4096_decoder.py
base-decryptor/decoders/base45_decoder.py
base-decryptor/decoders/base58_decoder.py
base-decryptor/decoders/base62_decoder.py
base-decryptor/decoders/base64_decoder.py
base-decryptor/decoders/base64_urlsafe_decoder.py
base-decryptor/decoders/base85_decoder.py
base-decryptor/decoders/base91_decoder.py
base-decryptor/decoders/hex_decoder.py
base-decryptor/decoders/uuencode_decoder.py
base-decryptor/utils/__init__.py
base-decryptor/utils/decode_all.py
base-decryptor/utils/decode_single_input.py
base-decryptor/utils/file_decoder.py
base-decryptor/utils/single_decoder.py
base_decrypter-0.2.0-py3.12.egg-info/PKG-INFO
base_decrypter-0.2.0-py3.12.egg-info/SOURCES.txt
base_decrypter-0.2.0-py3.12.egg-info/dependency_links.txt
base_decrypter-0.2.0-py3.12.egg-info/entry_points.txt
base_decrypter-0.2.0-py3.12.egg-info/requires.txt
base_decrypter-0.2.0-py3.12.egg-info/top_level.txt
base_decryptor/__init__.py
base_decryptor/main.py
base_decryptor/decoders/__init__.py
base_decryptor/decoders/ascii85_decoder.py
base_decryptor/decoders/base100_decoder.py
base_decryptor/decoders/base10_decoder.py
base_decryptor/decoders/base122_decoder.py
base_decryptor/decoders/base2_decoder.py
base_decryptor/decoders/base32_decoder.py
base_decryptor/decoders/base36_decoder.py
base_decryptor/decoders/base4096_decoder.py
base_decryptor/decoders/base45_decoder.py
base_decryptor/decoders/base58_decoder.py
base_decryptor/decoders/base62_decoder.py
base_decryptor/decoders/base64_decoder.py
base_decryptor/decoders/base64_urlsafe_decoder.py
base_decryptor/decoders/base85_decoder.py
base_decryptor/decoders/base8_decoder.py
base_decryptor/decoders/base91_decoder.py
base_decryptor/decoders/base92_decoder.py
base_decryptor/decoders/hex_decoder.py
base_decryptor/decoders/uuencode_decoder.py
base_decryptor/utils/__init__.py
base_decryptor/utils/decode_all.py
base_decryptor/utils/decode_single_input.py
base_decryptor/utils/file_decoder.py
base_decryptor/utils/single_decoder.py
base_decrypter-0.2.0.dist-info/dependency_links.txt
base_decrypter-0.2.0.dist-info/entry_points.txt
base_decrypter-0.2.0.dist-info/top_level.txt
base_decrypter-0.2.1.dist-info/METADATA
base_decrypter-0.2.1.dist-info/WHEEL
base_decrypter-0.2.1.dist-info/entry_points.txt
base_decrypter-0.2.1.dist-info/top_level.txt
base_decrypter-0.2.1.dist-info/RECORD
