Metadata-Version: 2.1
Name: base-decrypter
Version: 0.2.1
Summary: A CLI tool to automatically detect and decode base-encoded strings.
Home-page: https://github.com/aaryan-11-x/base-decryptor
Author: Aaryan Golatkar
Author-email: aaryangolatkar@gmail.com
Classifier: Programming Language :: Python :: 3
Classifier: License :: OSI Approved :: MIT License
Classifier: Operating System :: OS Independent
Requires-Python: >=3.12
Requires-Dist: base36 ==0.1.1
Requires-Dist: base4096 ==1.0
Requires-Dist: base45 ==0.4.4
Requires-Dist: base58 ==2.1.1
Requires-Dist: base91 ==1.0.1
Requires-Dist: base92 ==1.0.3
Requires-Dist: pybase100 ==0.3.1
Requires-Dist: click ==8.1.7
Requires-Dist: colorama ==0.4.6
Requires-Dist: emoji ==2.14.0
Requires-Dist: pybase62 ==1.0.0
Requires-Dist: pycryptodome ==3.20.0
Requires-Dist: pyfiglet ==1.0.2
Requires-Dist: requests ==2.32.3
Requires-Dist: rich ==13.9.3
Requires-Dist: tabulate ==0.9.0
Requires-Dist: yaspin ==3.1.0
